ratvision/__init__.py
ratvision/blender_script.py
ratvision/renderer.py
ratvision/environments/__init__.py
ratvision/environments/box_messy.blend
ratvision/environments/circle.png
ratvision/environments/floor_texture.webp
ratvision/environments/triangle.webp
ratvision/environments/wall_concrete1.jpg
ratvision/environments/wall_concrete2.jpg
ratvision/environments/wall_concrete3.webp
ratvision/environments/wall_texture.jpg
ratvision-0.1.1.dist-info/licenses/LICENSE
ratvision-0.1.1.dist-info/METADATA
ratvision-0.1.1.dist-info/WHEEL
ratvision-0.1.1.dist-info/top_level.txt
ratvision-0.1.1.dist-info/RECORD
