Metadata-Version: 2.4
Name: ratvision
Version: 0.1.1
Summary: A simple package for rat vision rendering simulation.
Author-email: "Marco P. Abrate" <marcopietro.abrate@gmail.com>
Project-URL: Homepage, https://github.com/marcoabrate/ratvision
Project-URL: Bug Tracker, https://github.com/marcoabrate/ratvision/issues
Project-URL: Documentation, https://github.com/marcoabrate/ratvision#readme
Keywords: vision,rat,simulation,rendering
Classifier: Programming Language :: Python :: 3
Classifier: License :: OSI Approved :: MIT License
Classifier: Operating System :: OS Independent
Requires-Python: >=3.7
License-File: LICENSE
Requires-Dist: matplotlib
Requires-Dist: pillow
Requires-Dist: importlib-resources; python_version < "3.9"
Dynamic: license-file
